leetnode/__init__.py
leetnode-1.0.3.dist-info/LICENSE
leetnode-1.0.3.dist-info/METADATA
leetnode-1.0.3.dist-info/WHEEL
leetnode-1.0.3.dist-info/top_level.txt
leetnode-1.0.3.dist-info/RECORD
