Metadata-Version: 2.1
Name: leetnode
Version: 1.0.3
Summary: A small Python 3.5+ library to make debugging LeetCode binary tree, linked list and matrix problems more convenient.
Home-page: https://github.com/MQDuck/LeetNode
Author: Jeffrey Thomas Piercy
Author-email: mqduck@mqduck.net
License: UNKNOWN
Platform: UNKNOWN
Classifier: Programming Language :: Python :: 3
Classifier: License :: OSI Approved :: MIT License
Classifier: Operating System :: OS Independent
Requires-Python: >=3.5
